mi2tsunocardgames/__init__.py
mi2tsunocardgames/deck.py
mi2tsunocardgames/blackjack/__init__.py
mi2tsunocardgames/blackjack/game.py
mi2tsunocardgames/highlow/__init__.py
mi2tsunocardgames/highlow/game.py
tests/__init__.py
tests/test_blackjack_game.py
tests/test_deck.py
tests/test_highlow_game.py
mi2tsunocardgames-0.1.0.dist-info/LICENSE.txt
mi2tsunocardgames-0.1.0.dist-info/METADATA
mi2tsunocardgames-0.1.0.dist-info/WHEEL
mi2tsunocardgames-0.1.0.dist-info/top_level.txt
mi2tsunocardgames-0.1.0.dist-info/RECORD
